pysysjava/__init__.py
pysysjava/coverage.py
pysysjava/javaplugin.py
pysysjava/junittest.py
pysysjava/junitxml.py
PySys_Java-0.1.dist-info/CHANGELOG.rst
PySys_Java-0.1.dist-info/LICENSE
PySys_Java-0.1.dist-info/METADATA
PySys_Java-0.1.dist-info/ProjectOverview.rst
PySys_Java-0.1.dist-info/WHEEL
PySys_Java-0.1.dist-info/top_level.txt
PySys_Java-0.1.dist-info/RECORD
