Metadata-Version: 2.1
Name: PySys-Java
Version: 0.1
Summary: Java plugins for the PySys System Test Framework
Home-page: https://github.com/ben-spiller/pysysjava
Author: Ben Spiller
License: Public Domain
Project-URL: Repository, https://github.com/ben-spiller/pysysjava
Project-URL: Sample, https://github.com/ben-spiller/pysysjava/tree/main/sample
Project-URL: Documentation, https://ben-spiller.github.io/pysysjava/
Keywords: pysys,java,junit
Platform: Operating System :: OS Independent
Platform: Operating System :: Microsoft :: Windows
Platform: Operating System :: POSIX :: Linux
Platform: Operating System :: MacOS
Classifier: License :: Public Domain
Classifier: Development Status :: 4 - Beta
Classifier: Intended Audience :: Developers
Classifier: Environment :: Plugins
Classifier: Intended Audience :: Developers
Classifier: Topic :: Software Development :: Quality Assurance
Classifier: Topic :: Software Development :: Testing
Classifier: Topic :: Software Development :: Testing :: Unit
Classifier: Topic :: Education :: Testing
Classifier: Programming Language :: Python
Classifier: Programming Language :: Python :: 3.6
Classifier: Programming Language :: Python :: 3.7
Classifier: Programming Language :: Python :: 3.8
Classifier: Programming Language :: Python :: Implementation :: CPython
Classifier: Natural Language :: English
Classifier: Operating System :: OS Independent
Classifier: Operating System :: Microsoft :: Windows
Classifier: Operating System :: POSIX :: Linux
Classifier: Operating System :: MacOS
Requires-Python: >=3.6, <4
Requires-Dist: PySys (>=1.6.1)
